{"name":"Forgot Password","id":"login-forgot-password;forgot-password","testSteps":[{"number":1,"description":"When Click on Forgot Button Link","duration":2119,"startTime":"2022-08-24T15:31:31.328677800+05:30[Asia/Calcutta]","result":"SUCCESS","precondition":false,"level":0},{"number":2,"description":"And Enter Linked Phone number","duration":2171,"startTime":"2022-08-24T15:31:33.450338900+05:30[Asia/Calcutta]","result":"SUCCESS","precondition":false,"level":0},{"number":3,"description":"And Click on Send Otp Button","duration":116,"startTime":"2022-08-24T15:31:35.622714300+05:30[Asia/Calcutta]","result":"SUCCESS","precondition":false,"level":0},{"number":4,"description":"Then Navigated to forgot password otp page","duration":8085,"startTime":"2022-08-24T15:31:35.740063+05:30[Asia/Calcutta]","result":"SUCCESS","precondition":false,"level":0},{"number":5,"description":"And Enter otp number","duration":2124,"startTime":"2022-08-24T15:31:43.828334800+05:30[Asia/Calcutta]","result":"SUCCESS","precondition":false,"level":0},{"number":6,"description":"And Click on Save Changes Button","duration":148,"startTime":"2022-08-24T15:31:45.955306+05:30[Asia/Calcutta]","result":"SUCCESS","precondition":false,"level":0},{"number":7,"description":"Then Navigated to create new password page","duration":8073,"startTime":"2022-08-24T15:31:46.106197600+05:30[Asia/Calcutta]","result":"SUCCESS","precondition":false,"level":0},{"number":8,"description":"And Create new Password","duration":2321,"startTime":"2022-08-24T15:31:54.180038900+05:30[Asia/Calcutta]","result":"SUCCESS","precondition":false,"level":0},{"number":9,"description":"And Click on Change Password Button","duration":64,"startTime":"2022-08-24T15:31:56.501891200+05:30[Asia/Calcutta]","result":"SUCCESS","precondition":false,"level":0}],"userStory":{"id":"login-forgot-password","storyName":"Login Forgot Password","displayName":"Login Forgot Password","path":"file:///C:/Users/Abhinav%20Kashyap/IdeaProjects/Member_Portal/src/main/resources/Feature/Login_Forgot_Password_Positive_Scenario.feature","type":"feature"},"featureTag":{"name":"Feature/Login Forgot Password","type":"feature","displayName":"Feature/Login Forgot Password"},"title":"Forgot Password","description":"","startTime":"2022-08-24T15:31:31.317895500+05:30[Asia/Calcutta]","duration":25248,"projectKey":"","isManualTestingUpToDate":false,"manual":false,"testSource":"Cucumber","result":"SUCCESS"}